MANIFEST.in
README.rst
setup.py
decorouter/__init__.py
decorouter/router.py
decorouter.egg-info/PKG-INFO
decorouter.egg-info/SOURCES.txt
decorouter.egg-info/dependency_links.txt
decorouter.egg-info/top_level.txt
decorouter/test/__init__.py
decorouter/test/test_router.py