Metadata-Version: 1.1
Name: decorouter
Version: 0.0.2
Summary: A WSGI routing apparatus.
Home-page: https://github.com/dhain/decorouter
Author: David Zuwenden
Author-email: dhain@zognot.org
License: MIT
Keywords: wsgi route
Platform: UNKNOWN
Classifier: Intended Audience :: Developers
Classifier: License :: OSI Approved :: MIT License
Classifier: Programming Language :: Python
Classifier: Topic :: Software Development :: Libraries :: Python Modules
Requires: webob
